{
  "Commands": [
    {
      "SemanticQueryDataShapeCommand": {
        "Query": {
          "Version": 2,
          "From": [
            {
              "Name": "c",
              "Entity": "Customer",
              "Type": 0
            }
          ],
          "Select": [
            {
              "Column": {
                "Expression": {
                  "SourceRef": {
                    "Source": "c"
                  }
                },
                "Property": "Customer"
              },
              "Name": "Customer.Customer"
            }
          ]
        },
        "Binding": {
          "Primary": {
            "Groupings": [
              {
                "Projections": [
                  0
                ]
              }
            ]
          },
          "DataReduction": {
            "DataVolume": 3,
            "Primary": {
              "Window": {}
            }
          },
          "IncludeEmptyGroups": true,
          "Version": 1
        },
        "ExecutionMetricsKind": 1
      }
    }
  ]
}